Metadata-Version: 2.1
Name: washi
Version: 0.0.1
Summary: Scripts to easily organize research
Home-page: UNKNOWN
Author: Kobi Felton
Author-email: kobi.c.f@gmail.com
License: UNKNOWN
Platform: UNKNOWN
Classifier: Development Status :: 3 - Alpha
Classifier: Topic :: Utilities
